{
"Short Weapons": {
  "Max": 1,
  "Cost": 1
},

"One-Handed Weapons": {
  "Max": 1,
  "Cost": 2,
  "Prereq": {
    "Short Weapons": 1
  }
},

"Two-Handed Weapons": {
  "Max": 1,
  "Cost": 3,
  "Prereq": {
    "One-Handed Weapons": 1
  }
},

"Oversized Weapon Use": {
  "Max": 1,
  "Cost": 2,
  "Prereq": {
    "Two-Handed Weapons": 1
  }
},

"Thrown Weapons": {
  "Max": 1,
  "Cost": 2
},

"Bow and Arrow": {
  "Max": 1,
  "Cost": 3
},

"Two-Weapon Fighting": {
  "Max": 1,
  "Cost": 6
},
"Armor Proficencies":{
  "Armor Training: Light": {
    "Max": 1,
    "Cost": 2
  },

  "Armor Training: Heavy": {
    "Max": 1,
    "Cost": 6,
    "Prereq": {
      "Armor Training: Light": 1
    }
  },

  "Shield Use": {
    "Max": 1,
    "Cost": 2
  },

  "Helmet Mastery": {
    "Max": 1,
    "Cost": 2
  }
},
"General Combat Skills":{
  "Toughness": {
    "Max": 5,
    "Cost": 6
  },

  "Dodge": {
    "Max": null,
    "Cost": 6
  },

  "Willpower": {
    "Max": null,
    "Cost": 4
  },

  "Parry": {
    "Max": null,
    "Cost": 4
  },

  "Guardian": {
    "Max": 1,
    "Cost": 4,
    "Prereq": {
      "Parry": 1
    }
  },

  "Stamina Training": {
    "Max": 1,
    "Cost": 2
  },

  "Great Stamina": {
    "Max": 1,
    "Cost": 4,
    "Prereq": {
      "Stamina Training": 1
    }
  },

  "Great Strike": {
    "Max": null,
    "Cost": 3
  },

  "Tactical Lunge": {
    "Max": 1,
    "Cost": 8,
    "Prereq": {
      "Great Strike": 1,
      "Parry": 1
    }
  },
  "Stun": {
    "Max": null,
    "Cost": 3
  }
},
"Archery":{
  "Precision": {
    "Max": 1,
    "Cost": 7,
    "Prereq": {
      "Bow and Arrow": 1
    }
  },

  "Master Precision": {
    "Max": 1,
    "Cost": 7,
    "Prereq": {
      "Precision": 1
    }
  },

  "Disarming Shot": {
    "Max": null,
    "Cost": 4,
    "Prereq": {
      "Precision": 1
    }
  },

  "Pinning Shot": {
    "Max": null,
    "Cost": 2,
    "Prereq": {
      "Precision": 1
    }
  },

  "Repelling Shot": {
    "Max": null,
    "Cost": 2,
    "Prereq": {
      "Pinning Shot": 1
    }
  },

  "One Shot, One Kill": {
    "Max": null,
    "Cost": 5,
    "Prereq": {
      "Master Precision": 1,
      "Repelling Shot": 1
    }
  },

  "Volley": {
    "Max": 1,
    "Cost": 10,
    "Prereq": {
      "Master Precision": 1
    }
  },

  "Faster Than the Eye": {
    "Max": 1,
    "Cost": 8,
    "Prereq": {
      "Master Precision": 1,
      "Stealth Attack": 1
    }
  }
},
"Officer Training":{
  "Sudden Motivation": {
    "Max": null,
    "Cost": 1
  },

  "Inspirational Speech": {
    "Max": null,
    "Cost": 2
  },

  "Defensive Instruction": {
    "Max": null,
    "Cost": 4,
    "Prereq": {
      "Parry": 1
    }
  },

  "Evasive Instruction": {
    "Max": null,
    "Cost": 6,
    "Prereq": {
      "Dodge": 1
    }
  },

  "Offensive Instruction": {
    "Max": null,
    "Cost": 3,
    "Prereq": {
      "Great Strike": 1
    }
  },

  "Military Drill": {
    "Max": 1,
    "Cost": 10,
    "Prereq": {"can_instruct":1}
  },

  "Self-Observation": {
    "Max": 1,
    "Cost": 4,
    "Prereq": {"can_instruct":1}
  }
},
"The Art of Dueling":{
  "Disarm": {
    "Max": null,
    "Cost": 4
  },

  "Feint": {
    "Max": null,
    "Cost": 1
  },

  "Invoke Challenge": {
    "Max": 1,
    "Cost": 5
  },

  "Salute": {
    "Max": 1,
    "Cost": 4
  },

  "Stylish Hat": {
    "Max": 1,
    "Cost": 2,
    "Prereq": {
      "Salute": 1
    }
  },

  "Witty Repartee": {
    "Max": 1,
    "Cost": 7
  },

  "Blade Dance": {
    "Max": null,
    "Cost": 5,
    "Prereq": {
      "Great Strike": 1,
      "Leap": 1
    }
  },

  "Pure Of Heart": {
    "Max": 1,
    "Cost": 3
  }
},
"The School of Suffering":{
  "Armored Forearms": {
    "Max": 1,
    "Cost": 6
  },

  "Armored Shins": {
    "Max": 1,
    "Cost": 9,
    "Prereq": {
      "Armored Forearms": 1
    }
  },

  "Slow Bleeding": {
    "Max": 1,
    "Cost": 3
  },

  "Meditative Stillness": {
    "Max": 1,
    "Cost": 2,
    "Prereq": {
      "Slow Bleeding": 1
    }
  },

  "Slow Death": {
    "Max": 1,
    "Cost": 3,
    "Prereq": {
      "Meditative Stillness": 1
    }
  },

  "Torture Resistance": {
    "Max": null,
    "Cost": 3
  },

  "Torture Immunity": {
    "Max": 1,
    "Cost": 4,
    "Prereq": {
      "Torture Resistance": 3
    }
  }
},
"The Assassin's Art":{
  "Stealth Attack": {
    "Max": 1,
    "Cost": 6,
    "Prereq": {"can_assassinate":1}
  },

  "10-Damage Strike": {
    "Max": null,
    "Cost": 8,
    "Prereq": {"can_assassinate":1}
  },

  "Studied Killer": {
    "Max": 1,
    "Cost": 6,
    "Prereq": {
      "Stealth Attack": 1
    }
  },

  "Twist the Knife": {
    "Max": 1,
    "Cost": 10,
    "Prereq": {
      "Stealth Attack": 1
    }
  },

  "Shin Kick": {
    "Max": null,
    "Cost": 3,
    "Prereq": {
      "Stun": 1
    }
  },

  "Sand in Your Eyes": {
    "Max": null,
    "Cost": 3,
    "Prereq": {
      "Stun": 1
    }
  },

  "Hidden Weapon": {
    "Max": 1,
    "Cost": 3,
    "Prereq": {
      "Short Weapons": 1
    }
  },

  "Leap": {
    "Max": null,
    "Cost": 2
  },

  "Leap Attack": {
    "Max": null,
    "Cost": 3,
    "Prereq": {
      "Leap": 1
    }
  },

  "Deathly Vault": {
    "Max": 1,
    "Cost": 4,
    "Prereq": {
      "Stealth Attack": 1,
      "Leap": 1
    }
  },

  "Rope Use": {
    "Max": 1,
    "Cost": 3
  }
},
"The Honoured Path of the Berserker":{
  "Battle Rage": {
    "Max": 1,
    "Cost": 0
  },

  "Enduring Rage": {
    "Max": 1,
    "Cost": 6
  },

  "Hatred": {
    "Max": 1,
    "Cost": 4,
    "Prereq": {
      "Battle Rage": 1
    }
  },

  "Berserker": {
    "Max": 1,
    "Cost": 10,
    "Prereq": {
      "Hatred": 1
    }
  },

  "Break Limb": {
    "Max": null,
    "Cost": 5
  },

  "Break Shield": {
    "Max": 1,
    "Cost": 5,
    "Prereq": {
      "Break Limb": 1,
      "Two-Handed Weapons": 1
    }
  }
},
"Mundane Healing":{
  "Examine Wounds": {
    "Max": 1,
    "Cost": 2
  },

  "Detect Poison": {
    "Max": 1,
    "Cost": 2,
    "Prereq": {
      "Examine Wounds": 1
    }
  },

  "Administer Antidote": {
    "Max": null,
    "Cost": 2,
    "Prereq": {
      "Detect Poison": 1
    }
  },

  "Detect Disease": {
    "Max": 1,
    "Cost": 2,
    "Prereq": {
      "Examine Wounds": 1
    }
  },

  "Apply Pressure": {
    "Max": 1,
    "Cost": 1,
    "Prereq": {
      "Examine Wounds": 1
    }
  },

  "Set Bone": {
    "Max": 1,
    "Cost": 3,
    "Prereq": {
      "Apply Pressure": 1
    }
  },

  "Bandage": {
    "Max": 1,
    "Cost": 4,
    "Prereq": {
      "Set Bone": 1
    }
  },

  "Trauma Patch": {
    "Max": null,
    "Cost": 4,
    "Prereq": {
      "Bandage": 1
    }
  },

  "Surgery": {
    "Max": 1,
    "Cost": 5,
    "Prereq": {
      "Bandage": 1,
      "Lore: Anatomy": 1
    }
  },

  "Battlefield Medicine": {
    "Max": 1,
    "Cost": 2,
    "Prereq": {
      "Surgery": 1
    }
  }
},
"Religious Worship":{
    "Prayer":{
        "Max":1,
        "Cost":4
    },
    "Secondary Prayer":{
        "Max":1,
        "Cost":4,
        "Prereq":{
            "Priesthood":2
        }
    },
    "Tertiary Prayer":{
        "Max":1,
        "Cost":4,
        "Prereq":{
            "Priesthood":4
        }
    },
    "Priesthood":{
        "Max":4,
        "Cost":6
    },
    "Rite Mastery":{
        "Max":1,
        "Cost":4,
        "Prereq":{"Prayer":1}
    },
    "Repentance":{
        "Max":1,
        "Cost":2
    }
},
"The Bardic Arts":{
  "Commanding Presence": {
    "Max": null,
    "Cost": 3
  },

  "Serenade": {
    "Max": null,
    "Cost": 8,
    "Prereq": {
      "Willpower": 1
    }
  },

  "Dance Lesson": {
    "Max": null,
    "Cost": 8,
    "Prereq": {
      "Dodge": 1
    }
  },

  "True Greatness": {
    "Max": null,
    "Cost": 4
  },

  "Drinking Song": {
    "Max": 1,
    "Cost": 6
  },

  "Meditative Song": {
    "Max": null,
    "Cost": 10,
    "Prereq": {
      "Mana Focus": 3
    }
  },

  "Hymn": {
    "Max": 1,
    "Cost": 2
  },

  "Requiem": {
    "Max": 1,
    "Cost": 3
  }
},
"Magical Arts":{
    "Mana Focus":{
        "Max":null,
        "Cost":1,
        "Prereq":{"Magical Aptitude":1}
    },
    "Alchemy":{
        "Max":4,
        "Cost":6
    },
    "Channeling":{
        "Max":4,
        "Cost":6
    },
    "Divination":{
        "Max":4,
        "Cost":6
    },
    "Sorcery":{
        "Max":4,
        "Cost":6
    },
    "Warding":{
        "Max":4,
        "Cost":6
    },
    "Weapon Casting":{
        "Max":1,
        "Cost":8,
        "Prereq":{"Magical Aptitude":1}
    },
    "Elemental Flourish":{
        "Max":1,
        "Cost":4,
        "Prereq":{"Sorcery":1,"Great Strike":1}
    },
    "Armored Casting":{
        "Max":1,
        "Cost":6,
        "Prereq":{"Magical Aptitude":1}
    },
    "Combat Mimic":{
        "Max":null,
        "Cost":4,
        "Prereq":{"Weapon Casting":1}
    },
    "Internal Reserves":{
        "Max":1,
        "Cost":4,
        "Prereq":{"Mana Focus":10}
    },
    "Arcane Tutelage":{
        "Max":1,
        "Cost":10,
        "Prereq":{"gm_mage":1,"research":1}
    },
    "Arcane Observation":{
        "Max":1,
        "Cost":4,
        "Prereq":{"Arcane Tutelage":1}
    },
    "Spellwright":{
        "Max":1,
        "Cost":2,
        "Prereq":{"gm_mage":1,"research":1}
    }
},
"Skullduggery":{
  "Disguise": {
    "Max": 1,
    "Cost": 4
  },

  "Master Disguise": {
    "Max": 1,
    "Cost": 6,
    "Prereq": {
      "Disguise": 1
    }
  },

  "Detect Disguise": {
    "Max": 1,
    "Cost": 4
  },

  "Escape": {
    "Max": null,
    "Cost": 3
  },

  "Poison Resistance": {
    "Max": null,
    "Cost": 2
  },

  "Poison Immunity": {
    "Max": 1,
    "Cost": 4,
    "Prereq": {
      "Poison Resistance": 3
    }
  },
  "Lockpicking": {
    "Max": 1,
    "Cost": 4
  },
  "Gambling": {
    "Max": null,
    "Cost": 2
  },
  "Torture": {
    "Max": null,
    "Cost": 2
  }
},
"Knowledge":{
    "Lore":{
        "Max":1,
        "Cost":4
    },
    "Research":{
        "Max":1,
        "Cost":6,
        "Prereq":{"Literate":1}
    },
    "Alchemical Examination":{
        "Max":1,
        "Cost":3,
        "Prereq":{"Lore: Alchemy":1}
    }
},
"Gathering":{
    "Academic Standing":{
        "Max":4,
        "Cost":4
    },
    "Economic Standing":{
        "Max":4,
        "Cost":4
    },
    "Military Standing":{
        "Max":4,
        "Cost":4
    },
    "Political Standing":{
        "Max":4,
        "Cost":4
    },
    "Underworld Standing":{
        "Max":4,
        "Cost":4
    },
    "Mining":{
        "Max":4,
        "Cost":4
    },
    "Herbalism":{
        "Max":4,
        "Cost":4
    },
    "Woodcutting":{
        "Max":4,
        "Cost":4
    },
    "Hunting":{
        "Max":4,
        "Cost":4
    },
    "Mercantile":{
        "Max":4,
        "Cost":4
    },
    "Black Market":{
        "Max":4,
        "Cost":4
    }
},
"Crafting Skills":{
    "Fortify Armor":{
        "Max":1,
        "Cost":3,
        "Prereq":{"can_fortify":1}
    },
    "Field Repair":{
        "Max":null,
        "Cost":2,
        "Prereq":{"can_field_repair":1}
    },
    "Repair Shield":{
        "Max":1,
        "Cost":3,
        "Prereq":{"Shieldsmithing":1}
    },
    "Recipe Scribing":{
        "Max":1,
        "Cost":2,
        "Prereq":{"Scroll Scribing":1}
    },
    "New Edition":{
        "Max":1,
        "Cost":3,
        "Prereq":{"Scroll Scribing":1}
    },
    "Grand Feast":{
        "Max":1,
        "Cost":10,
        "Prereq":{"Cooking":4}
    },
    "Reconstruct":{
        "Max":1,
        "Cost":1,
        "Prereq":{"is_crafter":1}
    },
    "Inventor":{
        "Max":1,
        "Cost":2,
        "Prereq":{"can_invent":1,"research":1}
    }
},
"Crafting Circles":{
    "Crafts":["Blacksmithing","Weaponsmithing","Armorsmithing","Shieldsmithing","Locksmithing","Enchanting","Scroll Scribing","Artificing","Cooking","Stable Alchemy","Tailoring","Fletching","Engineering"]
}
}